plover_last_translation.py
plover_last_translation-0.0.2.dist-info/DESCRIPTION.rst
plover_last_translation-0.0.2.dist-info/METADATA
plover_last_translation-0.0.2.dist-info/RECORD
plover_last_translation-0.0.2.dist-info/WHEEL
plover_last_translation-0.0.2.dist-info/entry_points.txt
plover_last_translation-0.0.2.dist-info/metadata.json
plover_last_translation-0.0.2.dist-info/top_level.txt
plover_last_translation-0.0.2.dist-info/zip-safe
